TVcrawler/__init__.py
TVcrawler-0.1.data/scripts/TVcrawler
TVcrawler-0.1.dist-info/DESCRIPTION.rst
TVcrawler-0.1.dist-info/METADATA
TVcrawler-0.1.dist-info/RECORD
TVcrawler-0.1.dist-info/WHEEL
TVcrawler-0.1.dist-info/metadata.json
TVcrawler-0.1.dist-info/top_level.txt
