Metadata-Version: 2.0
Name: TVcrawler
Version: 0.1
Summary: 
Requires-Dist: requests
